setup.cfg
setup.py
fetchr_stream/__init__.py
fetchr_stream/kinesis.py
fetchr_stream/stream_utils.py
fetchr_stream.egg-info/PKG-INFO
fetchr_stream.egg-info/SOURCES.txt
fetchr_stream.egg-info/dependency_links.txt
fetchr_stream.egg-info/requires.txt
fetchr_stream.egg-info/top_level.txt