Metadata-Version: 1.1
Name: fetchr-stream
Version: 0.2.0
Summary: Wrapper for pushing the data into streams
Home-page: https://https://github.com/fetchr/fetchr-stream
Author: Manoj Kumar
Author-email: harish224227@gmail.com
License: MIT
Download-URL: https://github.com/fetchr/fetchr-stream/archive/0.1.1.tar.gz
Keywords: streams,kinesis
Platform: UNKNOWN
